cleanup_dungeondraft_asset_packs.py
cleanup_dungeondraft_asset_packs-0.1.1.dist-info/entry_points.txt
cleanup_dungeondraft_asset_packs-0.1.1.dist-info/LICENSE
cleanup_dungeondraft_asset_packs-0.1.1.dist-info/WHEEL
cleanup_dungeondraft_asset_packs-0.1.1.dist-info/METADATA
cleanup_dungeondraft_asset_packs-0.1.1.dist-info/RECORD
