Metadata-Version: 2.1
Name: cleanup-dungeondraft-asset-packs
Version: 0.1.1
Summary: CLI tool to clean up Dungeondraft asset packs
Home-page: https://github.com/brouberol/cleanup-dungeondraft-asset-packs
License: MIT
Keywords: Dungeondraft
Author: Balthazar Rouberol
Author-email: br@imap.cc
Requires-Python: >=3.6,<4.0
Classifier: License :: OSI Approved :: MIT License
Classifier: Programming Language :: Python :: 3
Classifier: Programming Language :: Python :: 3 :: Only
Classifier: Programming Language :: Python :: 3.6
Classifier: Programming Language :: Python :: 3.7
Classifier: Programming Language :: Python :: 3.8
Classifier: Programming Language :: Python :: 3.9
Project-URL: Repository, https://github.com/brouberol/cleanup-dungeondraft-asset-packs
